{
  "en": {
    "common.loading": "Loading...",
    "common.language": "Language",
    "common.theme": "Theme",
    "common.light": "Light",
    "common.dark": "Dark",
    "common.english": "English",
    "common.indonesian": "Indonesia",
    "common.retry": "Retry",
    "auth.loggedInAs": "Logged in as",
    "auth.signOut": "Sign Out",
    "auth.email": "Email",
    "auth.password": "Password",
    "auth.emailPlaceholder": "you@example.com",
    "auth.passwordPlaceholder": "••••••••",
    "auth.pleaseWait": "Please wait...",
    "auth.signIn": "Sign In",
    "auth.signInToContinue": "Sign in to continue",
    "auth.createAccount": "Create Account",
    "auth.createYourAccount": "Create your account",
    "auth.continueAsGuest": "Continue as Guest",
    "auth.alreadyHaveAccount": "Already have an account?",
    "auth.dontHaveAccount": "Don't have an account?",
    "auth.createOne": "Create one",
    "quran.surah": "Surah",
    "quran.ayah": "Ayah",
    "quran.reveal": "Show Hint",
    "quran.hideHint": "Hide Hint",
    "quran.rateWithoutReveal": "Rate directly or use hint if needed.",
    "quran.revealNextPhrase": "Reveal Next Phrase",
    "quran.autoAdvanceCountdown": "Auto-advance in",
    "quran.forceSkipReveal": "Force Skip Reveal",
    "quran.autoplayBlockedFallback": "Autoplay was blocked. Tap Play if needed while countdown continues.",
    "quran.audioNotSupported": "Your browser does not support audio playback.",
    "rating.again": "Again",
    "rating.hard": "Hard",
    "rating.good": "Good",
    "rating.easy": "Easy",
    "page.practice": "Practice",
    "page.activeSource": "From",
    "page.chooseSource": "Choose Source",
    "page.sourceSheetTitle": "Start From",
    "page.searchSurah": "Search surah",
    "page.searchPackage": "Search package",
    "page.noSurahMatch": "No surah found for your search.",
    "page.noPackageMatch": "No package found for your search.",
    "page.page": "Page",
    "page.of": "of",
    "page.prev": "Prev",
    "page.next": "Next",
    "page.infoControl": "Info",
    "page.guestPackageStatusNote": "Package status is saved locally in guest mode.",
    "page.learningPackages": "Learning Packages",
    "page.learningPackagesDescription": "Follow a curated memorization plan or jump into any surah directly.",
    "page.showPackages": "Show",
    "page.hidePackages": "Hide",
    "page.noPublishedPackages": "No published packages found.",
    "page.status": "Status",
    "page.statusActive": "Active",
    "page.statusPaused": "Paused",
    "page.statusCompleted": "Completed",
    "page.statusNotStarted": "Not Started",
    "page.progress": "Progress",
    "page.dailyNewTarget": "Daily new target",
    "page.dailyLimitReached": "Daily new verse limit reached for this package. Target",
    "page.showingPackageDue": "Showing due reviews for selected package",
    "page.targetIncrease": "Increase target",
    "page.targetDecrease": "Decrease target",
    "page.start": "Start",
    "page.resume": "Resume",
    "page.pause": "Pause",
    "page.complete": "Complete",
    "page.chooseSurah": "Choose your surah",
    "page.chooseSurahDescription": "Start practice from the first ayah of any surah.",
    "page.openSurah": "Open surah",
    "page.currentSurah": "Current surah",
    "page.dueReviews": "Due Reviews Today",
    "page.loadingDueQueue": "Loading due queue...",
    "page.ayahDueSingular": "ayah due",
    "page.ayahDuePlural": "ayahs due",
    "page.loadFallbackAyah": "Load Fallback Ayah",
    "page.nextReviewAuto": "Moves to the next ayah after rating.",
    "page.loadingAyah": "Loading ayah from Quran.com...",
    "page.savingReview": "Saving review locally...",
    "page.ef": "EF",
    "page.interval": "Interval",
    "page.reps": "Reps",
    "page.dataSource": "Data source",
    "page.disclaimer": "Disclaimer",
    "page.checkMushaf": "Always verify your recitation and text against your mushaf.",
    "page.credit": "Credit",
    "page.quranTextSource": "Quran.com verse and audio data",
    "page.methodology": "Memorization methodology",
    "page.practiceSectionTitle": "Practice workspace",
    "page.activeTracksTitle": "Active tracks",
    "page.addTracks": "Add tracks",
    "page.noActiveTracks": "No active tracks yet. Add one to continue.",
    "page.trackTypePackage": "Package",
    "page.trackTypeSurah": "Surah",
    "page.trackReset": "Reset track",
    "page.trackPlay": "Start track",
    "page.historySectionTitle": "History and progress",
    "page.lastReviewSnapshot": "Latest review snapshot",
    "page.methodologyStep1": "Recall first without looking, then use the hint only when needed.",
    "page.methodologyStep2": "Rate your recall honestly with Again, Hard, Good, or Easy.",
    "page.methodologyStep3": "Review repeatedly over time using spaced repetition so weaker ayat return sooner.",
    "page.ankiInspired": "Inspired by Anki's spaced-repetition workflow, adapted for Quran memorization and murajaah.",
    "page.ankiLink": "Anki official website",
    "page.learnAboutMethodology": "How it works",
    "page.feedback": "Feedback",
    "page.statsTab": "Stats",
    "page.statsTitle": "Practice stats",
    "page.statsDescription": "A quick snapshot of how your murajaah is progressing right now.",
    "page.totalReviewedVerses": "Verses reviewed",
    "page.newToday": "New today",
    "page.dueNow": "Due now",
    "page.activePackagesCount": "Active packages",
    "page.completedPackagesCount": "Completed packages",
    "page.averageEf": "Average EF",
    "page.relearningBadge": "Relearning",
    "page.relearningAttempt": "Attempt",
    "page.relearningQueue": "Immediate relearning",
    "page.relearningVerseSingular": "ayah in relearning",
    "page.relearningVersePlural": "ayahs in relearning",
    "page.relearningPriority": "Failed ayat will repeat before moving forward.",
    "page.surahMasteryTitle": "Surah mastery",
    "page.surahMasteryDescription": "Track your progress through each surah with forward and random recall mastery.",
    "page.surahProgress": "Progress",
    "page.surahNew": "New",
    "page.surahLearning": "Learning",
    "page.surahMastered": "Mastered",
    "page.forwardMasteryBadge": "Forward Mastered",
    "page.forwardMasteryLabel": "Can recite consecutive ayahs",
    "page.randomMasteryBadge": "Random Access Mastered",
    "page.randomMasteryLabel": "Can recall random ayahs",
    "page.surahCompletionTitle": "Surah Mastered!",
    "page.completionStats": "Your achievement",
    "page.totalAyahs": "Ayahs mastered",
    "page.recallAccuracy": "Recall accuracy",
    "page.nextReviewSuggestion": "Next review in",
    "page.days": "days",
    "page.completionMessage": "You've built strong recall for this entire surah. Rest well and return when ready.",
    "page.takeSuggestedBreak": "Take a break",
    "page.nextSurah": "Next surah",
    "page.takeBreak": "Take a break",
    "page.resumePractice": "Resume practice",
    "page.breakTitle": "Taking a well-deserved break",
    "page.breakMessage": "Rest your mind and eyes. Return when you're ready to continue.",
    "page.breakSuggestion": "Come back in a few minutes to maintain your rhythm.",
    "page.feedbackDescription": "Help improve Murajaah by sharing bugs, ideas, or suggestions.",
    "page.feedbackCta": "Open feedback form",
    "page.infoCenter": "Info center",
    "page.sourceTab": "Source",
    "page.creditTab": "Credit",
    "page.legalTab": "Legal",
    "page.feedbackTab": "Feedback",
    "page.closeModal": "Close",
    "page.openInfoCenter": "Open info center",
    "page.sourceDescription": "Murajaah uses Quran.com for verse text and audio playback.",
    "page.creditDescription": "Built by Ali Qornan and Muhammad Jafar as a focused murajaah companion for lightweight daily review.",
    "page.guestMode": "Guest mode",
    "page.localOnly": "local only",
    "page.privacyTitle": "Privacy",
    "page.privacyBody": "Guest-mode progress stays on your device. Signed-in usage stores only the review data needed to run your memorization history and package status.",
    "page.termsTitle": "Terms",
    "page.termsBody": "Murajaah is a study aid. Please verify recitation and text against your mushaf and use the app responsibly as a personal memorization companion.",
    "practice.backToHome": "Back",
    "practice.reciteAyah": "Recite the ayah",
    "practice.showHint": "Show Hint",
    "practice.showAyah": "Show Ayah",
    "practice.nextPhrase": "Next Phrase",
    "practice.prevPhrase": "Prev Phrase",
    "practice.sessionComplete": "Session complete!",
    "practice.sessionCompleteSubtitle": "Returning to home...",
    "practice.noReviews": "No reviews due",
    "practice.noReviewsSubtitle": "You're all caught up for this track.",
    "practice.dueReviewTitle": "Due Review",
    "practice.autoAdvance": "Auto-advance in",
    "practice.forceSkip": "Skip ahead",
    "practice.dueCard.title": "Ayahs due for review",
    "practice.dueCard.subtitle": "Combined across all your active tracks",
    "practice.dueCard.cta": "Start Review",
    "practice.dueCard.allCaughtUp": "You're all caught up!",
    "practice.dueCard.allCaughtUpSubtitle": "No ayahs due right now. Keep up the good work.",
    "practice.dueCard.loading": "Checking due reviews..."
  },
  "id": {
    "common.loading": "Memuat...",
    "common.language": "Bahasa",
    "common.theme": "Tema",
    "common.light": "Terang",
    "common.dark": "Gelap",
    "common.english": "Inggris",
    "common.indonesian": "Indonesia",
    "common.retry": "Coba Lagi",
    "auth.loggedInAs": "Masuk sebagai",
    "auth.signOut": "Keluar",
    "auth.email": "Email",
    "auth.password": "Kata Sandi",
    "auth.emailPlaceholder": "anda@contoh.com",
    "auth.passwordPlaceholder": "••••••••",
    "auth.pleaseWait": "Mohon tunggu...",
    "auth.signIn": "Masuk",
    "auth.signInToContinue": "Masuk untuk melanjutkan",
    "auth.createAccount": "Buat Akun",
    "auth.createYourAccount": "Buat akun Anda",
    "auth.continueAsGuest": "Lanjut sebagai Tamu",
    "auth.alreadyHaveAccount": "Sudah punya akun?",
    "auth.dontHaveAccount": "Belum punya akun?",
    "auth.createOne": "Buat akun",
    "quran.surah": "Surah",
    "quran.ayah": "Ayat",
    "quran.reveal": "Tampilkan Hint",
    "quran.hideHint": "Sembunyikan Hint",
    "quran.rateWithoutReveal": "Nilai langsung atau gunakan hint bila perlu.",
    "quran.revealNextPhrase": "Tampilkan Frasa Berikutnya",
    "quran.autoAdvanceCountdown": "Lanjut otomatis dalam",
    "quran.forceSkipReveal": "Lewati Reveal",
    "quran.autoplayBlockedFallback": "Autoplay diblokir browser. Ketuk Putar bila perlu sambil countdown tetap berjalan.",
    "quran.audioNotSupported": "Browser Anda tidak mendukung pemutaran audio.",
    "rating.again": "Ulang",
    "rating.hard": "Sulit",
    "rating.good": "Baik",
    "rating.easy": "Mudah",
    "page.practice": "Latihan",
    "page.activeSource": "Dari",
    "page.chooseSource": "Pilih Sumber",
    "page.sourceSheetTitle": "Mulai Dari",
    "page.searchSurah": "Cari surah",
    "page.searchPackage": "Cari paket",
    "page.noSurahMatch": "Surah tidak ditemukan untuk pencarian Anda.",
    "page.noPackageMatch": "Paket tidak ditemukan untuk pencarian Anda.",
    "page.page": "Halaman",
    "page.of": "dari",
    "page.prev": "Sebelumnya",
    "page.next": "Berikutnya",
    "page.infoControl": "Info",
    "page.guestPackageStatusNote": "Status paket disimpan secara lokal saat mode tamu.",
    "page.learningPackages": "Paket Pembelajaran",
    "page.learningPackagesDescription": "Ikuti paket hafalan terkurasi atau langsung pilih surah mana pun.",
    "page.showPackages": "Tampilkan",
    "page.hidePackages": "Sembunyikan",
    "page.noPublishedPackages": "Belum ada paket yang dipublikasikan.",
    "page.status": "Status",
    "page.statusActive": "Aktif",
    "page.statusPaused": "Jeda",
    "page.statusCompleted": "Selesai",
    "page.statusNotStarted": "Belum Mulai",
    "page.progress": "Progres",
    "page.dailyNewTarget": "Target ayat baru harian",
    "page.dailyLimitReached": "Batas ayat baru harian untuk paket ini tercapai. Target",
    "page.showingPackageDue": "Menampilkan tinjauan jatuh tempo untuk paket yang dipilih",
    "page.targetIncrease": "Tambah target",
    "page.targetDecrease": "Kurangi target",
    "page.start": "Mulai",
    "page.resume": "Lanjut",
    "page.pause": "Jeda",
    "page.complete": "Selesai",
    "page.chooseSurah": "Pilih surah Anda",
    "page.chooseSurahDescription": "Mulai murajaah dari ayat pertama surah mana pun.",
    "page.openSurah": "Buka surah",
    "page.currentSurah": "Surah saat ini",
    "page.dueReviews": "Tinjauan Jatuh Tempo Hari Ini",
    "page.loadingDueQueue": "Memuat antrean tinjauan...",
    "page.ayahDueSingular": "ayat jatuh tempo",
    "page.ayahDuePlural": "ayat jatuh tempo",
    "page.loadFallbackAyah": "Muat Ayat Cadangan",
    "page.nextReviewAuto": "Berpindah ke ayat berikutnya setelah penilaian.",
    "page.loadingAyah": "Memuat ayat dari Quran.com...",
    "page.savingReview": "Menyimpan tinjauan secara lokal...",
    "page.ef": "EF",
    "page.interval": "Interval",
    "page.reps": "Pengulangan",
    "page.dataSource": "Sumber data",
    "page.disclaimer": "Disclaimer",
    "page.checkMushaf": "Selalu verifikasi bacaan dan teks dengan mushaf Anda.",
    "page.credit": "Kredit",
    "page.quranTextSource": "Data ayat dan audio dari Quran.com",
    "page.methodology": "Metodologi hafalan",
    "page.practiceSectionTitle": "Ruang latihan",
    "page.activeTracksTitle": "Track aktif",
    "page.addTracks": "Tambah track",
    "page.noActiveTracks": "Belum ada track aktif. Tambahkan untuk melanjutkan.",
    "page.trackTypePackage": "Paket",
    "page.trackTypeSurah": "Surah",
    "page.trackReset": "Reset track",
    "page.trackPlay": "Mulai track",
    "page.historySectionTitle": "Riwayat dan progres",
    "page.lastReviewSnapshot": "Ringkasan review terakhir",
    "page.methodologyStep1": "Coba ingat dulu tanpa melihat, lalu gunakan hint hanya bila perlu.",
    "page.methodologyStep2": "Nilai hafalan secara jujur dengan Ulang, Sulit, Baik, atau Mudah.",
    "page.methodologyStep3": "Ulangi murajaah dari waktu ke waktu dengan spaced repetition agar ayat yang lemah muncul lebih cepat.",
    "page.ankiInspired": "Terinspirasi dari alur spaced repetition Anki, lalu disesuaikan untuk hafalan Quran dan murajaah.",
    "page.ankiLink": "Situs resmi Anki",
    "page.learnAboutMethodology": "Cara kerjanya",
    "page.feedback": "Masukan",
    "page.statsTab": "Statistik",
    "page.statsTitle": "Statistik latihan",
    "page.statsDescription": "Ringkasan singkat tentang perkembangan murajaah Anda saat ini.",
    "page.totalReviewedVerses": "Ayat yang sudah ditinjau",
    "page.newToday": "Ayat baru hari ini",
    "page.dueNow": "Jatuh tempo saat ini",
    "page.activePackagesCount": "Paket aktif",
    "page.completedPackagesCount": "Paket selesai",
    "page.averageEf": "Rata-rata EF",
    "page.relearningBadge": "Ulangi",
    "page.relearningAttempt": "Percobaan",
    "page.relearningQueue": "Pengulangan langsung",
    "page.relearningVerseSingular": "ayat dalam pengulangan",
    "page.relearningVersePlural": "ayat dalam pengulangan",
    "page.relearningPriority": "Ayat yang gagal akan diulang sebelum lanjut ke ayat berikutnya.",
    "page.surahMasteryTitle": "Penguasaan surah",
    "page.surahMasteryDescription": "Lacak kemajuanmu melalui setiap surah dengan penguasaan ingatan forward dan random.",
    "page.surahProgress": "Progres",
    "page.surahNew": "Baru",
    "page.surahLearning": "Sedang dipelajari",
    "page.surahMastered": "Dikuasai",
    "page.forwardMasteryBadge": "Forward Dikuasai",
    "page.forwardMasteryLabel": "Dapat melafalkan ayat berturut-turut",
    "page.randomMasteryBadge": "Random Akses Dikuasai",
    "page.randomMasteryLabel": "Dapat mengingat ayat acak",
    "page.surahCompletionTitle": "Surah Dikuasai!",
    "page.completionStats": "Pencapaianmu",
    "page.totalAyahs": "Ayat yang dikuasai",
    "page.recallAccuracy": "Akurasi ingatan",
    "page.nextReviewSuggestion": "Review berikutnya dalam",
    "page.days": "hari",
    "page.completionMessage": "Kamu telah membangun ingatan yang kuat untuk seluruh surah ini. Istirahat dengan baik dan kembali saat siap.",
    "page.takeSuggestedBreak": "Istirahat dulu",
    "page.nextSurah": "Surah berikutnya",
    "page.takeBreak": "Istirahat",
    "page.resumePractice": "Lanjut murajaah",
    "page.breakTitle": "Mengambil istirahat yang layak",
    "page.breakMessage": "Istirahatkan pikiran dan mata Anda. Kembali saat Anda siap melanjutkan.",
    "page.breakSuggestion": "Kembali dalam beberapa menit untuk mempertahankan ritme Anda.",
    "page.feedbackDescription": "Bantu tingkatkan Murajaah dengan melaporkan bug, ide, atau saran.",
    "page.feedbackCta": "Buka formulir masukan",
    "page.infoCenter": "Pusat info",
    "page.sourceTab": "Sumber",
    "page.creditTab": "Kredit",
    "page.legalTab": "Legal",
    "page.feedbackTab": "Masukan",
    "page.closeModal": "Tutup",
    "page.openInfoCenter": "Buka pusat info",
    "page.sourceDescription": "Murajaah menggunakan Quran.com untuk teks ayat dan pemutaran audio.",
    "page.creditDescription": "Dibangun oleh Ali Qornan dan Muhammad Jafar sebagai pendamping murajaah yang ringan dan fokus untuk review harian.",
    "page.guestMode": "Mode tamu",
    "page.localOnly": "lokal saja",
    "page.privacyTitle": "Privasi",
    "page.privacyBody": "Progress mode tamu tetap di perangkat Anda. Saat masuk, aplikasi hanya menyimpan data review yang diperlukan untuk riwayat hafalan dan status paket Anda.",
    "page.termsTitle": "Ketentuan",
    "page.termsBody": "Murajaah adalah alat bantu belajar. Mohon verifikasi bacaan dan teks dengan mushaf Anda serta gunakan aplikasi ini secara bijak sebagai pendamping hafalan pribadi.",
    "practice.backToHome": "Kembali",
    "practice.reciteAyah": "Lafalkan ayat ini",
    "practice.showHint": "Tampilkan Petunjuk",
    "practice.showAyah": "Tampilkan Ayat",
    "practice.nextPhrase": "Frasa Berikutnya",
    "practice.prevPhrase": "Frasa Sebelumnya",
    "practice.sessionComplete": "Sesi selesai!",
    "practice.sessionCompleteSubtitle": "Kembali ke beranda...",
    "practice.noReviews": "Tidak ada tinjauan",
    "practice.noReviewsSubtitle": "Semua tinjauan untuk jalur ini sudah selesai.",
    "practice.dueReviewTitle": "Tinjauan Jatuh Tempo",
    "practice.autoAdvance": "Lanjut otomatis dalam",
    "practice.forceSkip": "Lewati",
    "practice.dueCard.title": "Ayat jatuh tempo",
    "practice.dueCard.subtitle": "Gabungan dari semua jalur aktif Anda",
    "practice.dueCard.cta": "Mulai Tinjauan",
    "practice.dueCard.allCaughtUp": "Semua sudah selesai!",
    "practice.dueCard.allCaughtUpSubtitle": "Tidak ada ayat yang jatuh tempo saat ini. Pertahankan semangatmu.",
    "practice.dueCard.loading": "Memeriksa tinjauan..."
  }
}
